setup.py
rozipparser/__init__.py
rozipparser/parser.py
rozipparser.egg-info/PKG-INFO
rozipparser.egg-info/SOURCES.txt
rozipparser.egg-info/dependency_links.txt
rozipparser.egg-info/pbr.json
rozipparser.egg-info/requires.txt
rozipparser.egg-info/top_level.txt
rozipparser/codeparser/__init__.py
rozipparser/codeparser/code_parser.py
rozipparser/model/__init__.py
rozipparser/model/code.py
rozipparser/tests/__init__.py
rozipparser/tests/test_bucharest_parsing.py
rozipparser/tests/test_combined_parsing.py
rozipparser/tests/test_large_locality_parsing.py
rozipparser/tests/test_small_locality_parsing.py