Metadata-Version: 1.1
Name: rozipparser
Version: 0.2.1
Summary: Parse official zip code documents from the Romanian Government
Home-page: https://github.com/macostea/RoZipParser
Author: Mihai Costea
Author-email: mihai.andrei.costea@icloud.com
License: MIT
Keywords: zip code development parser romania
Platform: UNKNOWN
Classifier: Development Status :: 3 - Alpha
Classifier: Intended Audience :: Developers
Classifier: Topic :: Software Development :: Libraries
Classifier: License :: OSI Approved :: MIT License
Classifier: Programming Language :: Python :: 2.7
Classifier: Programming Language :: Python :: 3.3
Classifier: Programming Language :: Python :: 3.4
Classifier: Programming Language :: Python :: 3.5
